{"id":"160650243","responseA":"I can see the image depicts a wine label. On the label, there are illustrations that may resemble vines or grapevine motifs, which are commonly associated with wine labels. I do not see any definitive animals or humans on the label. On a scale of 0 to 1, with 0 being 'not certain at all' and 1 being 'very certain', I am 1, or 'very certain', that the image is of a wine label and the depicted illustrations do not clearly represent animals or humans.","responseB":"{"animal": "none", "certainty": 1.0}"}