{"id":"164943553","responseA":"The image displays a bottle of wine with a label that reads "MOSMIERI Saperavi Qvevri." The label features a line drawing at the top which appears to depict a rural scene with a building, possibly a historical or traditional structure, but I do not see any animals or humans in the drawing. My certainty regarding the absence of animals or humans in the drawing is 1, as I can confidently state what is depicted based on the visual elements present.","responseB":"{"animal": "none","certainty": 1}"}