{"id":"171209949","responseA":"There is an illustration of a human on the wine label. The human figure appears to be a woman dressed in a traditional shooting outfit, complete with a hat, and she seems to be carrying a shotgun. The woman is positioned in a landscape with trees and is accompanied by a dog, which suggests hunting or outdoor activity. Additionally, there are birds in the sky, which might be the game she is hunting. My certainty level about the presence of a human and an animal in this image is 1, which means I am very certain.","responseB":"{"animal": "human, dog, birds", "certainty": 1}"}